[
    {
        "hostelName": "Kngh",
        "menu": null,
        "messCommittee": null,
        "warden": "null",
        "accountant": null,
        "noOfStudent": 0
    },
    {
        "hostelName": "Tilak",
        "menu": null,
        "messCommittee": null,
        "warden": "null",
        "accountant": null,
        "noOfStudent": 0
    },
    {
        "hostelName": "Malviya",
        "menu": null,
        "messCommittee": null,
        "warden": "null",
        "accountant": null,
        "noOfStudent": 0
    },
    {
        "hostelName": "Tandon",
        "menu": null,
        "messCommittee": null,
        "warden": "null",
        "accountant": null,
        "noOfStudent": 0
    },
    {
        "hostelName": "Djgh",
        "menu": null,
        "messCommittee": null,
        "warden": "null",
        "accountant": null,
        "noOfStudent": 0
    },
    {
        "hostelName": "Tagore",
        "menu": null,
        "messCommittee": null,
        "warden": "null",
        "accountant": null,
        "noOfStudent": 0
    },
    {
        "hostelName": "Svbh",
        "menu": null,
        "messCommittee": null,
        "warden": "null",
        "accountant": null,
        "noOfStudent": 0
    },
    {
        "hostelName": "Raman",
        "menu": null,
        "messCommittee": null,
        "warden": "null",
        "accountant": null,
        "noOfStudent": 0
    },
    {
        "hostelName": "Sngh",
        "menu": null,
        "messCommittee": null,
        "warden": "null",
        "accountant": null,
        "noOfStudent": 0
    },
    {
        "hostelName": "Patel",
        "menu": null,
        "messCommittee": null,
        "warden": "null",
        "accountant": null,
        "noOfStudent": 0
    }
]